ksimpleapi/__init__.py
ksimpleapi/api.py
ksimpleapi/request.py
ksimpleapi-0.0.41.dist-info/METADATA
ksimpleapi-0.0.41.dist-info/WHEEL
ksimpleapi-0.0.41.dist-info/top_level.txt
ksimpleapi-0.0.41.dist-info/RECORD
