Metadata-Version: 2.1
Name: ksimpleapi
Version: 0.0.41
Summary: ksimpleapi
Home-page: https://github.com/kkristof200/py_simpleapi
Author: Kristof
License: UNKNOWN
Platform: UNKNOWN
Classifier: Programming Language :: Python :: 3
Classifier: License :: OSI Approved :: MIT License
Classifier: Operating System :: OS Independent
Requires-Python: >=3.5
